{
  "label": "2026-06-28",
  "date": "2026-06-28",
  "generated_at": "2026-06-28T21:11:53",
  "count": 1,
  "papers": [
    {
      "paper_id": "202606/28/2606.21753v1-scene-level-heterogeneous-physics-simulation-with-3d-gaussian-splats",
      "section": "deep",
      "title_en": "Scene-Level Heterogeneous Physics Simulation with 3D Gaussian Splats",
      "authors": "Xiaoyang Liu, Shangzhe Wu, Kai Han",
      "date": "2026-06-19",
      "pdf": "https://arxiv.org/pdf/2606.21753v1",
      "score": "8.0",
      "evidence": "3D高斯泼溅用于逼真渲染与物理仿真",
      "tldr": "3D Gaussian Splatting (3DGS) 虽能逼真渲染，但缺乏物理交互能力。现有方法局限于物体级且无法处理异构场景。本文提出表示抽象框架，将 3DGS、网格、流体等资产统一为物理粒子集，通过求解器模拟后映射回视觉重建。首次实现场景级异构物理模拟，支持可变形 3DGS 与流体、网格及静态环境的双向交互，显著扩展了 3DGS 的应用范围。",
      "tags": "query:pano-dgs",
      "abstract_en": "3D Gaussian Splatting (3DGS) has achieved state-of-the-art photorealistic rendering, but the representation gap prevents these assets from being physically interactive. Production-grade physics engines do not understand the 3DGS representation, while prior physics-for-3DGS methods are monolithic silos. These prior works are fundamentally limited, demonstrating only object-centric physics in isolated environments, such as on an ideal plane. They are incapable of interacting with complex static collision geometry or heterogeneous assets. We propose a novel framework that, for the first time, bridges this gap by enabling 3DGS assets to participate in scene-level, heterogeneous, multi-solver physical simulations. Our core contribution is a Representation Abstraction Framework that translates all diverse assets, including 3DGS, virtual meshes, and fluids, into a unified physical particle set. This abstraction is key to enabling complex behaviors, such as the non-rigid deformation of 3DGS assets, within a unified physics pipeline. This particle set, along with the static scene collision boundaries derived from scene capture, is processed within a solver-agnostic physics kernel. The physical results are then mapped back to drive each asset's specific visual reconstruction. This architecture unlocks capabilities impossible with prior art. We demonstrate complex, two-way interactions between deformable 3DGS assets, standard CG assets such as fluids and meshes, and large-scale captured static environments, showcasing realistic coupled phenomena that were previously unattainable.",
      "source": "arxiv",
      "selection_source": "fresh_fetch"
    }
  ],
  "errors": []
}
